stubb/__init__.py
stubb-0.1.dist-info/LICENSE
stubb-0.1.dist-info/METADATA
stubb-0.1.dist-info/WHEEL
stubb-0.1.dist-info/top_level.txt
stubb-0.1.dist-info/RECORD
