Metadata-Version: 2.1
Name: stubb
Version: 0.1
Summary: Structured LLM outputs and evals
Author: Mark Neumann
License: Apache-2.0
Project-URL: Homepage, https://github.com/deneutoy/stubb
Project-URL: Changelog, https://github.com/deneutoy/stubb/releases
Project-URL: Issues, https://github.com/deneutoy/stubb/issues
Project-URL: CI, https://github.com/deneutoy/stubb/actions
Classifier: License :: OSI Approved :: Apache Software License
Requires-Python: >=3.8
License-File: LICENSE
Provides-Extra: test
Requires-Dist: pytest ; extra == 'test'
